validator/__init__.py
validator/bundle.py
validator/bundler.py
validator/postprocess.py
validator/utils.py
validator/validator.py
validator/test/__init__.py
validator/test/fixtures.py
validator/test/test_resourceref.py
validator/test/test_validator.py
qontract_validator-0.1.0.dist-info/METADATA
qontract_validator-0.1.0.dist-info/WHEEL
qontract_validator-0.1.0.dist-info/entry_points.txt
qontract_validator-0.1.0.dist-info/top_level.txt
qontract_validator-0.1.0.dist-info/RECORD
